__init__.py
mcp_foundry/__init__.py
mcp_foundry/__main__.py
mcp_foundry/logging_config.py
mcp_foundry/mcp_server.py
mcp_foundry/mcp_foundry_evaluation/tools.py
mcp_foundry/mcp_foundry_finetuning/swagger.py
mcp_foundry/mcp_foundry_finetuning/tools.py
mcp_foundry/mcp_foundry_knowledge/__init__.py
mcp_foundry/mcp_foundry_knowledge/prompts.py
mcp_foundry/mcp_foundry_knowledge/resources.py
mcp_foundry/mcp_foundry_knowledge/tools.py
mcp_foundry/mcp_foundry_knowledge/data_access_objects/__init__.py
mcp_foundry/mcp_foundry_knowledge/data_access_objects/dao.py
mcp_foundry/mcp_foundry_knowledge/data_access_objects/models.py
mcp_foundry/mcp_foundry_model/__init__.py
mcp_foundry/mcp_foundry_model/models.py
mcp_foundry/mcp_foundry_model/tools.py
mcp_foundry/mcp_foundry_model/utils.py
mseep_mcp_foundry-0.1.1.dist-info/licenses/LICENSE
mseep_mcp_foundry-0.1.1.dist-info/METADATA
mseep_mcp_foundry-0.1.1.dist-info/WHEEL
mseep_mcp_foundry-0.1.1.dist-info/entry_points.txt
mseep_mcp_foundry-0.1.1.dist-info/top_level.txt
mseep_mcp_foundry-0.1.1.dist-info/RECORD
