Metadata-Version: 2.4
Name: mseep-mcp-foundry
Version: 0.1.1
Summary: MCP Server for Azure AI Foundry (experimental)
Author-email: mseep <support@skydeck.ai>
Requires-Python: >=3.10
License-File: LICENSE
Requires-Dist: mcp>=1.8.0
Requires-Dist: requests>=2.32.3
Requires-Dist: azure-mgmt-cognitiveservices>=13.0.0
Requires-Dist: azure-identity>=1.0
Requires-Dist: jinja2~=3.0
Requires-Dist: azure-search-documents>=11.5.2
Requires-Dist: azure-cli>=2.60.0
Requires-Dist: azure-ai-evaluation>=1.9.0
Requires-Dist: azure-ai-projects>=1.0.0b11
Dynamic: license-file
